mfconv/__init__.py
mfconv/plotter.py
mfconv-0.2.7.dist-info/LICENSE.txt
mfconv-0.2.7.dist-info/METADATA
mfconv-0.2.7.dist-info/WHEEL
mfconv-0.2.7.dist-info/top_level.txt
mfconv-0.2.7.dist-info/RECORD
