Metadata-Version: 2.1
Name: mfconv
Version: 0.2.7
Summary: a python package to plot modflow convergence while you run a model
Home-page: https://github.com/gmezacuadra/mfconv
Author: Gustavo Meza-Cuadra
Author-email: gmeza-cuadra@flosolutions.com
License: MIT
Classifier: License :: OSI Approved :: MIT License
Classifier: Programming Language :: Python
Classifier: Programming Language :: Python :: 3
Classifier: Programming Language :: Python :: 3.5
Classifier: Programming Language :: Python :: 3.6
Classifier: Programming Language :: Python :: 3.7
Classifier: Programming Language :: Python :: 3.8
Classifier: Programming Language :: Python :: 3.9
License-File: LICENSE.txt
